agavepy/__init__.py
agavepy/actors.py
agavepy/agave.py
agavepy/async.py
agavepy/resource_exceptions.json
agavepy/resources.json
agavepy/response_handlers.py
agavepy/clients/__init__.py
agavepy/clients/create.py
agavepy/clients/delete.py
agavepy/clients/exceptions.py
agavepy/clients/list.py
agavepy/clients/subscribe.py
agavepy/clients/subscribtions.py
agavepy/files/__init__.py
agavepy/files/copy.py
agavepy/files/delete.py
agavepy/files/download.py
agavepy/files/exceptions.py
agavepy/files/history.py
agavepy/files/import_files.py
agavepy/files/list.py
agavepy/files/mkdir.py
agavepy/files/move.py
agavepy/files/pems_delete.py
agavepy/files/pems_list.py
agavepy/files/pems_update.py
agavepy/files/upload.py
agavepy/resources/api_actors.json.j2
agavepy/resources/api_admin.json.j2
agavepy/resources/api_apps.json.j2
agavepy/resources/api_clients.json.j2
agavepy/resources/api_files.json.j2
agavepy/resources/api_jobs.json.j2
agavepy/resources/api_meta.json.j2
agavepy/resources/api_monitors.json.j2
agavepy/resources/api_notifications.json.j2
agavepy/resources/api_postits.json.j2
agavepy/resources/api_profiles.json.j2
agavepy/resources/api_systems.json.j2
agavepy/resources/api_transforms.json.j2
agavepy/resources/deprecated_resources.json.j2
agavepy/resources/misc.json.j2
agavepy/swaggerpy/__init__.py
agavepy/swaggerpy/client.py
agavepy/swaggerpy/codegen.py
agavepy/swaggerpy/http_client.py
agavepy/swaggerpy/processors.py
agavepy/swaggerpy/swagger_model.py
agavepy/tenants/__init__.py
agavepy/tenants/tenants.py
agavepy/tokens/__init__.py
agavepy/tokens/create_access_token.py
agavepy/tokens/exceptions.py
agavepy/tokens/refresh_tokens.py
agavepy/utils/__init__.py
agavepy/utils/load_configs.py
agavepy/utils/response_handlers.py
agavepy/utils/save_configs.py
agavepy-0.9.5.data/data/requirements-py2.txt
agavepy-0.9.5.data/data/requirements.txt
agavepy-0.9.5.dist-info/AUTHORS
agavepy-0.9.5.dist-info/LICENSE
agavepy-0.9.5.dist-info/METADATA
agavepy-0.9.5.dist-info/WHEEL
agavepy-0.9.5.dist-info/top_level.txt
agavepy-0.9.5.dist-info/RECORD
