Metadata-Version: 2.1
Name: agavepy
Version: 0.9.5
Summary: SDK for Tapis
Home-page: https://github.com/TACC/agavepy
Author: Texas Advanced Computing Center
Author-email: jstubbs@tacc.utexas.edu, vaughn@tacc.utexas.edu
License: BSD
Platform: UNKNOWN
Classifier: Development Status :: 4 - Beta
Classifier: Intended Audience :: Developers
Classifier: License :: OSI Approved :: BSD License
Classifier: Natural Language :: English
Classifier: Programming Language :: Python :: 2
Classifier: Programming Language :: Python :: 2.7
Classifier: Programming Language :: Python :: 3
Classifier: Programming Language :: Python :: 3.3
Classifier: Programming Language :: Python :: 3.6
Classifier: Programming Language :: Python :: 3.7
Classifier: Programming Language :: Python :: 3.8
Requires-Dist: Jinja2 (>=2.7.3)
Requires-Dist: backports.ssl-match-hostname (>=3.4.0.2)
Requires-Dist: py (>=1.4.26)
Requires-Dist: pytest (>=2.7.0)
Requires-Dist: python-dateutil (>=2.4.2)
Requires-Dist: requests (>=2.6.0)
Requires-Dist: six (>=1.9.0)
Requires-Dist: websocket-client (==0.53.0)
Requires-Dist: requests-toolbelt (>=0.7.1)
Requires-Dist: future (>=0.16.0)
Requires-Dist: configparser (>=3.5.0)
Requires-Dist: cloudpickle (>=0.4.0)
